context_shield/__init__.py
context_shield/detect.py
context_shield/rewrite.py
utils/__init__.py
utils/detect.py
utils/rewrite.py
context_shield-0.1.0.dist-info/METADATA
context_shield-0.1.0.dist-info/WHEEL
context_shield-0.1.0.dist-info/top_level.txt
context_shield-0.1.0.dist-info/RECORD
