Metadata-Version: 2.4
Name: context-shield
Version: 0.1.0
Summary: AI tool for detecting toxic text and rewriting safely
Author: Your Name
Requires-Dist: textblob
Requires-Dist: transformers
Requires-Dist: torch
Dynamic: author
Dynamic: requires-dist
Dynamic: summary
